ewha_anomaly_detection/__init__ .py
ewha_anomaly_detection/anomaly_detection.py
ewha_anomaly_detection-0.1.9.dist-info/METADATA
ewha_anomaly_detection-0.1.9.dist-info/WHEEL
ewha_anomaly_detection-0.1.9.dist-info/top_level.txt
ewha_anomaly_detection-0.1.9.dist-info/RECORD
