Metadata-Version: 2.4
Name: ewha_anomaly_detection
Version: 0.1.9
Summary: An Pedestrian Trajectory Anomaly Detection for Python.
Author-email: Juyeon Cho <whwndus13@naver.com>
Requires-Python: >=3.8
Requires-Dist: numpy
Requires-Dist: pandas
Requires-Dist: geopandas
Requires-Dist: shapely
Requires-Dist: tensorflow
